aio_pydispatch/__init__.py
aio_pydispatch/signal.py
aio_pydispatch/utils.py
aio_pydispatch-1.0.0.dist-info/LICENSE
aio_pydispatch-1.0.0.dist-info/METADATA
aio_pydispatch-1.0.0.dist-info/WHEEL
aio_pydispatch-1.0.0.dist-info/top_level.txt
aio_pydispatch-1.0.0.dist-info/RECORD
