Metadata-Version: 2.1
Name: aio-pydispatch
Version: 1.0.0
Summary: asyncio pydipatch (Signal Manager)
Home-page: https://github.com/whg517/aio-pydispatch.git
Author: huagang517
Author-email: huagang517@126.com
License: UNKNOWN
Platform: UNKNOWN
Classifier: Intended Audience :: Developers
Classifier: Operating System :: OS Independent
Classifier: License :: OSI Approved :: MIT License
Classifier: Programming Language :: Python :: 3
Classifier: Programming Language :: Python :: 3.9
Classifier: Programming Language :: Python :: 3.10
Requires-Python: >=3.9
License-File: LICENSE
